tests/__init__.py
tests/test_simples.py
herolibsaraiva-0.1.0.dist-info/METADATA
herolibsaraiva-0.1.0.dist-info/WHEEL
herolibsaraiva-0.1.0.dist-info/top_level.txt
herolibsaraiva-0.1.0.dist-info/RECORD
