Metadata-Version: 2.4
Name: heroLibSaraiva
Version: 0.1.0
Summary: Biblioteca para gerenciamento de heróis e seus times.
Home-page: https://github.com/saraivagustavo/heroLibSaraiva
Author: Gustavo Saraiva Mariano
Author-email: gsaraivam10@gmail.com
License: MIT
Classifier: Programming Language :: Python :: 3
Classifier: License :: OSI Approved :: MIT License
Classifier: Operating System :: OS Independent
Requires-Python: >=3.8
Requires-Dist: sqlmodel
Requires-Dist: typing_extensions
Provides-Extra: dev
Requires-Dist: pytest>=7.0; extra == "dev"
Dynamic: author
Dynamic: author-email
Dynamic: classifier
Dynamic: description
Dynamic: description-content-type
Dynamic: home-page
Dynamic: license
Dynamic: provides-extra
Dynamic: requires-dist
Dynamic: requires-python
Dynamic: summary
